disvoice
notebooks_examples
