Metadata-Version: 2.1
Name: disvoice
Version: 0.1.8
Summary: Python framework designed to compute different types of features from speech files
Home-page: https://github.com/jcvasquezc/disvoice
Download-URL: https://github.com/jcvasquezc/disvoice/#files
Author: J. C. Vasquez-Correa
Author-email: juan.vasquez@fau.de
License: MIT
Project-URL: Source code, https://github.com/jcvasquezc/disvoice
Project-URL: Documentation, https://disvoice.readthedocs.io/en/latest/
Project-URL: Bug Tracker, https://github.com/jcvasquezc/DisVoice/issues
Keywords: speech,speech features,articulatory features,phoneme recognition,prosody,praat
Platform: UNKNOWN
Classifier: Development Status :: 4 - Beta
Classifier: Intended Audience :: Developers
Classifier: License :: OSI Approved :: MIT License
Classifier: Programming Language :: Python :: 3
Classifier: Programming Language :: Python :: 3.4
Classifier: Programming Language :: Python :: 3.5
Classifier: Programming Language :: Python :: 3.6
Classifier: Programming Language :: Python :: 3.7
Classifier: Programming Language :: Python :: 3.8
Classifier: Programming Language :: Python :: 3.9
Classifier: Programming Language :: Python :: 3.10
Classifier: Programming Language :: Python
Classifier: Topic :: Software Development
Classifier: Topic :: Scientific/Engineering
License-File: LICENSE
